setup.py
sapy/__init__.py
sapy/displmethod.py
sapy/element.py
sapy/gmsh.py
sapy/index.py
sapy/kinematics.py
sapy/load.py
sapy/plotter.py
sapy/stiffness.py
sapy/structure.py
sapy.egg-info/PKG-INFO
sapy.egg-info/SOURCES.txt
sapy.egg-info/dependency_links.txt
sapy.egg-info/not-zip-safe
sapy.egg-info/requires.txt
sapy.egg-info/top_level.txt