Metadata-Version: 1.1
Name: sapy
Version: 0.1
Summary: matrix structural analysis
Home-page: https://github.com/nasseralkmim/sapy
Author: Nasser Alkmim
Author-email: nasser.alkmim@gmail.com
License: MIT
Download-URL: https://github.com/nasseralkmim/sapy/releases/tag/0.1
Platform: UNKNOWN
